<?xml version="1.0" encoding="UTF-8"?>
<!DOCTYPE GranuleMetaDataFile SYSTEM "http://ecsinfo.gsfc.nasa.gov/ECSInfo/ecsmetadata/dtds/DPL/ECS/ScienceGranuleMetadata.dtd">
<GranuleMetaDataFile>
    <DTDVersion>1.0</DTDVersion>
    <DataCenterId>EDC</DataCenterId>
    <GranuleURMetaData>
        <GranuleUR>SC:MCD43B3.005:2248137145</GranuleUR>
        <DbID>2248137145</DbID>
        <InsertTime>2017-03-23 03:26:23.141</InsertTime>
        <LastUpdate>2017-03-24 02:12:28.028</LastUpdate>
        <CollectionMetaData>
            <ShortName>MCD43B3</ShortName>
            <VersionID>5</VersionID>
        </CollectionMetaData>
        <DataFiles>
            <DataFileContainer>
                <DistributedFileName>MCD43B3.A2017065.h28v05.005.2017082082142.hdf</DistributedFileName>
                <FileSize>12707669</FileSize>
                <ChecksumType>CKSUM</ChecksumType>
                <Checksum>3317566868</Checksum>
                <ChecksumOrigin>DPLIngst</ChecksumOrigin>
            </DataFileContainer>
        </DataFiles>
        <ECSDataGranule>
            <SizeMBECSDataGranule>12.119</SizeMBECSDataGranule>
            <ReprocessingPlanned>further update is anticipated</ReprocessingPlanned>
            <ReprocessingActual>reprocessed</ReprocessingActual>
            <LocalGranuleID>MCD43B3.A2017065.h28v05.005.2017082082142.hdf</LocalGranuleID>
            <DayNightFlag>Day</DayNightFlag>
            <ProductionDateTime>2017-03-23 08:21:42.000</ProductionDateTime>
            <LocalVersionID>5.0.6</LocalVersionID>
        </ECSDataGranule>
        <PGEVersionClass>
            <PGEVersion>5.0.16</PGEVersion>
        </PGEVersionClass>
        <RangeDateTime>
            <RangeEndingTime>23:59:59.999999</RangeEndingTime>
            <RangeEndingDate>2017-03-21</RangeEndingDate>
            <RangeBeginningTime>00:00:00.000000</RangeBeginningTime>
            <RangeBeginningDate>2017-03-06</RangeBeginningDate>
        </RangeDateTime>
        <SpatialDomainContainer>
            <HorizontalSpatialDomainContainer>
                <GPolygon>
                    <Boundary>
                        <Point>
                            <PointLongitude>115.279770612558</PointLongitude>
                            <PointLatitude>29.9120286077015</PointLatitude>
                        </Point>
                        <Point>
                            <PointLongitude>130.479894464731</PointLongitude>
                            <PointLatitude>40.0963659160409</PointLatitude>
                        </Point>
                        <Point>
                            <PointLongitude>143.625483713722</PointLongitude>
                            <PointLatitude>39.9980314725989</PointLatitude>
                        </Point>
                        <Point>
                            <PointLongitude>126.92618645292</PointLongitude>
                            <PointLatitude>29.8240282821481</PointLatitude>
                        </Point>
                    </Boundary>
                </GPolygon>
            </HorizontalSpatialDomainContainer>
        </SpatialDomainContainer>
        <MeasuredParameter>
            <MeasuredParameterContainer>
                <ParameterName>Albedo</ParameterName>
                <QAFlags>
                    <AutomaticQualityFlag>Passed</AutomaticQualityFlag>
                    <AutomaticQualityFlagExplanation>Passed was set as a default value. More algorithm will be developed</AutomaticQualityFlagExplanation>
                    <OperationalQualityFlag>Passed</OperationalQualityFlag>
                    <OperationalQualityFlagExplanation>Passed</OperationalQualityFlagExplanation>
                    <ScienceQualityFlag>Inferred Passed</ScienceQualityFlag>
                    <ScienceQualityFlagExplanation>Initial evaluations show good agreement with field data and appropriate quality flags. Users are advised to examine band specific quality bits before using data in science applications..2017-03-24 02:12</ScienceQualityFlagExplanation>
                </QAFlags>
            </MeasuredParameterContainer>
        </MeasuredParameter>
        <Platform>
            <PlatformShortName>Terra</PlatformShortName>
            <Instrument>
                <InstrumentShortName>MODIS</InstrumentShortName>
                <Sensor>
                    <SensorShortName>MODIS</SensorShortName>
                </Sensor>
            </Instrument>
        </Platform>
        <Platform>
            <PlatformShortName>Aqua</PlatformShortName>
            <Instrument>
                <InstrumentShortName>MODIS</InstrumentShortName>
                <Sensor>
                    <SensorShortName>MODIS</SensorShortName>
                </Sensor>
            </Instrument>
        </Platform>
        <PSAs>
            <PSA>
                <PSAName>QAPERCENTGOODQUALITY</PSAName>
                <PSAValue>9</PSAValue>
            </PSA>
            <PSA>
                <PSAName>QAPERCENTOTHERQUALITY</PSAName>
                <PSAValue>34</PSAValue>
            </PSA>
            <PSA>
                <PSAName>QAPERCENTNOTPRODUCEDCLOUD</PSAName>
                <PSAValue>0</PSAValue>
            </PSA>
            <PSA>
                <PSAName>QAPERCENTNOTPRODUCEDOTHER</PSAName>
                <PSAValue>57</PSAValue>
            </PSA>
            <PSA>
                <PSAName>HORIZONTALTILENUMBER</PSAName>
                <PSAValue>28</PSAValue>
            </PSA>
            <PSA>
                <PSAName>VERTICALTILENUMBER</PSAName>
                <PSAValue>05</PSAValue>
            </PSA>
            <PSA>
                <PSAName>TileID</PSAName>
                <PSAValue>51028005</PSAValue>
            </PSA>
            <PSA>
                <PSAName>BRDFCODEID</PSAName>
                <PSAValue>AMBRALS_V4.0R1</PSAValue>
            </PSA>
            <PSA>
                <PSAName>SETUPFILEID</PSAName>
                <PSAValue>6121997</PSAValue>
            </PSA>
            <PSA>
                <PSAName>ALBEDOFILEID</PSAName>
                <PSAValue>6121997</PSAValue>
            </PSA>
            <PSA>
                <PSAName>BRDFDATABASEVERSION</PSAName>
                <PSAValue>v1.0(500m)</PSAValue>
            </PSA>
            <PSA>
                <PSAName>PERCENTLANDINTILE</PSAName>
                <PSAValue>49.204143</PSAValue>
            </PSA>
            <PSA>
                <PSAName>PERCENTPROCESSEDINTILE</PSAName>
                <PSAValue>82.097312</PSAValue>
            </PSA>
            <PSA>
                <PSAName>PERCENTNEWBRDFS</PSAName>
                <PSAValue>25.263616</PSAValue>
            </PSA>
            <PSA>
                <PSAName>PERCENTSHAPEFIXEDBRDFS</PSAName>
                <PSAValue>56.833696</PSAValue>
            </PSA>
            <PSA>
                <PSAName>PERCENTSUBSTITUTEBRDFS</PSAName>
                <PSAValue>0.000000</PSAValue>
            </PSA>
            <PSA>
                <PSAName>AVERAGENUMBEROBS</PSAName>
                <PSAValue>3.677546</PSAValue>
            </PSA>
        </PSAs>
        <InputGranule>
            <InputPointer>MYD09GHK.A2017065.h28v05.005.2017067075428.hdf</InputPointer>
            <InputPointer>MYD09GST.A2017065.h28v05.005.2017067074957.hdf</InputPointer>
            <InputPointer>MYDMGGAD.A2017065.h28v05.005.2017067074106.hdf</InputPointer>
            <InputPointer>MYDPTHKM.A2017065.h28v05.005.2017067074059.hdf</InputPointer>
            <InputPointer>MYD09GHK.A2017066.h28v05.005.2017068063757.hdf</InputPointer>
            <InputPointer>MYD09GST.A2017066.h28v05.005.2017068063345.hdf</InputPointer>
            <InputPointer>MYDMGGAD.A2017066.h28v05.005.2017068063329.hdf</InputPointer>
            <InputPointer>MYDPTHKM.A2017066.h28v05.005.2017068063317.hdf</InputPointer>
            <InputPointer>MYD09GHK.A2017067.h28v05.005.2017073144953.hdf</InputPointer>
            <InputPointer>MYD09GST.A2017067.h28v05.005.2017073144612.hdf</InputPointer>
            <InputPointer>MYDMGGAD.A2017067.h28v05.005.2017073144552.hdf</InputPointer>
            <InputPointer>MYDPTHKM.A2017067.h28v05.005.2017073144546.hdf</InputPointer>
            <InputPointer>MYD09GHK.A2017068.h28v05.005.2017073040028.hdf</InputPointer>
            <InputPointer>MYD09GST.A2017068.h28v05.005.2017073035425.hdf</InputPointer>
            <InputPointer>MYDMGGAD.A2017068.h28v05.005.2017073035412.hdf</InputPointer>
            <InputPointer>MYDPTHKM.A2017068.h28v05.005.2017073035403.hdf</InputPointer>
            <InputPointer>MYD09GHK.A2017069.h28v05.005.2017071070437.hdf</InputPointer>
            <InputPointer>MYD09GST.A2017069.h28v05.005.2017071065839.hdf</InputPointer>
            <InputPointer>MYDMGGAD.A2017069.h28v05.005.2017071065822.hdf</InputPointer>
            <InputPointer>MYDPTHKM.A2017069.h28v05.005.2017071065814.hdf</InputPointer>
            <InputPointer>MYD09GHK.A2017070.h28v05.005.2017072073553.hdf</InputPointer>
            <InputPointer>MYD09GST.A2017070.h28v05.005.2017072072659.hdf</InputPointer>
            <InputPointer>MYDMGGAD.A2017070.h28v05.005.2017072071914.hdf</InputPointer>
            <InputPointer>MYDPTHKM.A2017070.h28v05.005.2017072071908.hdf</InputPointer>
            <InputPointer>MYD09GHK.A2017071.h28v05.005.2017073063641.hdf</InputPointer>
            <InputPointer>MYD09GST.A2017071.h28v05.005.2017073063306.hdf</InputPointer>
            <InputPointer>MYDMGGAD.A2017071.h28v05.005.2017073063244.hdf</InputPointer>
            <InputPointer>MYDPTHKM.A2017071.h28v05.005.2017073063236.hdf</InputPointer>
            <InputPointer>MYD09GHK.A2017072.h28v05.005.2017074235513.hdf</InputPointer>
            <InputPointer>MYD09GST.A2017072.h28v05.005.2017074235022.hdf</InputPointer>
            <InputPointer>MYDMGGAD.A2017072.h28v05.005.2017074234900.hdf</InputPointer>
            <InputPointer>MYDPTHKM.A2017072.h28v05.005.2017074234852.hdf</InputPointer>
            <InputPointer>MYD09GHK.A2017073.h28v05.005.2017075061951.hdf</InputPointer>
            <InputPointer>MYD09GST.A2017073.h28v05.005.2017075061200.hdf</InputPointer>
            <InputPointer>MYDMGGAD.A2017073.h28v05.005.2017075060242.hdf</InputPointer>
            <InputPointer>MYDPTHKM.A2017073.h28v05.005.2017075060235.hdf</InputPointer>
            <InputPointer>MYD09GHK.A2017074.h28v05.005.2017076061544.hdf</InputPointer>
            <InputPointer>MYD09GST.A2017074.h28v05.005.2017076061210.hdf</InputPointer>
            <InputPointer>MYDMGGAD.A2017074.h28v05.005.2017076061200.hdf</InputPointer>
            <InputPointer>MYDPTHKM.A2017074.h28v05.005.2017076061153.hdf</InputPointer>
            <InputPointer>MYD09GHK.A2017075.h28v05.005.2017077063939.hdf</InputPointer>
            <InputPointer>MYD09GST.A2017075.h28v05.005.2017077063109.hdf</InputPointer>
            <InputPointer>MYDMGGAD.A2017075.h28v05.005.2017077062818.hdf</InputPointer>
            <InputPointer>MYDPTHKM.A2017075.h28v05.005.2017077062806.hdf</InputPointer>
            <InputPointer>MYD09GHK.A2017076.h28v05.005.2017078065743.hdf</InputPointer>
            <InputPointer>MYD09GST.A2017076.h28v05.005.2017078065003.hdf</InputPointer>
            <InputPointer>MYDMGGAD.A2017076.h28v05.005.2017078064357.hdf</InputPointer>
            <InputPointer>MYDPTHKM.A2017076.h28v05.005.2017078064349.hdf</InputPointer>
            <InputPointer>MYD09GHK.A2017077.h28v05.005.2017079053227.hdf</InputPointer>
            <InputPointer>MYD09GST.A2017077.h28v05.005.2017079052555.hdf</InputPointer>
            <InputPointer>MYDMGGAD.A2017077.h28v05.005.2017079052254.hdf</InputPointer>
            <InputPointer>MYDPTHKM.A2017077.h28v05.005.2017079052243.hdf</InputPointer>
            <InputPointer>MYD09GHK.A2017078.h28v05.005.2017080052915.hdf</InputPointer>
            <InputPointer>MYD09GST.A2017078.h28v05.005.2017080052315.hdf</InputPointer>
            <InputPointer>MYDMGGAD.A2017078.h28v05.005.2017080052135.hdf</InputPointer>
            <InputPointer>MYDPTHKM.A2017078.h28v05.005.2017080052118.hdf</InputPointer>
            <InputPointer>MYD09GHK.A2017079.h28v05.005.2017081063522.hdf</InputPointer>
            <InputPointer>MYD09GST.A2017079.h28v05.005.2017081063157.hdf</InputPointer>
            <InputPointer>MYDMGGAD.A2017079.h28v05.005.2017081063148.hdf</InputPointer>
            <InputPointer>MYDPTHKM.A2017079.h28v05.005.2017081063139.hdf</InputPointer>
            <InputPointer>MYD09GHK.A2017080.h28v05.005.2017082072039.hdf</InputPointer>
            <InputPointer>MYD09GST.A2017080.h28v05.005.2017082071531.hdf</InputPointer>
            <InputPointer>MYDMGGAD.A2017080.h28v05.005.2017082071201.hdf</InputPointer>
            <InputPointer>MYDPTHKM.A2017080.h28v05.005.2017082071154.hdf</InputPointer>
            <InputPointer>MOD09GHK.A2017065.h28v05.005.2017067082650.hdf</InputPointer>
            <InputPointer>MOD09GST.A2017065.h28v05.005.2017067082301.hdf</InputPointer>
            <InputPointer>MODMGGAD.A2017065.h28v05.005.2017067082248.hdf</InputPointer>
            <InputPointer>MODPTHKM.A2017065.h28v05.005.2017067082241.hdf</InputPointer>
            <InputPointer>MOD09GHK.A2017066.h28v05.005.2017068061955.hdf</InputPointer>
            <InputPointer>MOD09GST.A2017066.h28v05.005.2017068060930.hdf</InputPointer>
            <InputPointer>MODMGGAD.A2017066.h28v05.005.2017068055125.hdf</InputPointer>
            <InputPointer>MODPTHKM.A2017066.h28v05.005.2017068055117.hdf</InputPointer>
            <InputPointer>MOD09GHK.A2017067.h28v05.005.2017069083252.hdf</InputPointer>
            <InputPointer>MOD09GST.A2017067.h28v05.005.2017069082821.hdf</InputPointer>
            <InputPointer>MODMGGAD.A2017067.h28v05.005.2017069082752.hdf</InputPointer>
            <InputPointer>MODPTHKM.A2017067.h28v05.005.2017069082742.hdf</InputPointer>
            <InputPointer>MOD09GHK.A2017068.h28v05.005.2017070093205.hdf</InputPointer>
            <InputPointer>MOD09GST.A2017068.h28v05.005.2017070092609.hdf</InputPointer>
            <InputPointer>MODMGGAD.A2017068.h28v05.005.2017070091606.hdf</InputPointer>
            <InputPointer>MODPTHKM.A2017068.h28v05.005.2017070091557.hdf</InputPointer>
            <InputPointer>MOD09GHK.A2017069.h28v05.005.2017071073337.hdf</InputPointer>
            <InputPointer>MOD09GST.A2017069.h28v05.005.2017071072905.hdf</InputPointer>
            <InputPointer>MODMGGAD.A2017069.h28v05.005.2017071072846.hdf</InputPointer>
            <InputPointer>MODPTHKM.A2017069.h28v05.005.2017071072837.hdf</InputPointer>
            <InputPointer>MOD09GHK.A2017070.h28v05.005.2017072055850.hdf</InputPointer>
            <InputPointer>MOD09GST.A2017070.h28v05.005.2017072055212.hdf</InputPointer>
            <InputPointer>MODMGGAD.A2017070.h28v05.005.2017072055029.hdf</InputPointer>
            <InputPointer>MODPTHKM.A2017070.h28v05.005.2017072054950.hdf</InputPointer>
            <InputPointer>MOD09GHK.A2017071.h28v05.005.2017073071129.hdf</InputPointer>
            <InputPointer>MOD09GST.A2017071.h28v05.005.2017073070751.hdf</InputPointer>
            <InputPointer>MODMGGAD.A2017071.h28v05.005.2017073070732.hdf</InputPointer>
            <InputPointer>MODPTHKM.A2017071.h28v05.005.2017073070724.hdf</InputPointer>
            <InputPointer>MOD09GHK.A2017072.h28v05.005.2017074071242.hdf</InputPointer>
            <InputPointer>MOD09GST.A2017072.h28v05.005.2017074070753.hdf</InputPointer>
            <InputPointer>MODMGGAD.A2017072.h28v05.005.2017074070623.hdf</InputPointer>
            <InputPointer>MODPTHKM.A2017072.h28v05.005.2017074070602.hdf</InputPointer>
            <InputPointer>MOD09GHK.A2017073.h28v05.005.2017075064925.hdf</InputPointer>
            <InputPointer>MOD09GST.A2017073.h28v05.005.2017075064514.hdf</InputPointer>
            <InputPointer>MODMGGAD.A2017073.h28v05.005.2017075064502.hdf</InputPointer>
            <InputPointer>MODPTHKM.A2017073.h28v05.005.2017075064447.hdf</InputPointer>
            <InputPointer>MOD09GHK.A2017074.h28v05.005.2017076054704.hdf</InputPointer>
            <InputPointer>MOD09GST.A2017074.h28v05.005.2017076054123.hdf</InputPointer>
            <InputPointer>MODMGGAD.A2017074.h28v05.005.2017076054113.hdf</InputPointer>
            <InputPointer>MODPTHKM.A2017074.h28v05.005.2017076054107.hdf</InputPointer>
            <InputPointer>MOD09GHK.A2017075.h28v05.005.2017077070226.hdf</InputPointer>
            <InputPointer>MOD09GST.A2017075.h28v05.005.2017077065926.hdf</InputPointer>
            <InputPointer>MODMGGAD.A2017075.h28v05.005.2017077065915.hdf</InputPointer>
            <InputPointer>MODPTHKM.A2017075.h28v05.005.2017077065909.hdf</InputPointer>
            <InputPointer>MOD09GHK.A2017076.h28v05.005.2017081010344.hdf</InputPointer>
            <InputPointer>MOD09GST.A2017076.h28v05.005.2017081005836.hdf</InputPointer>
            <InputPointer>MODMGGAD.A2017076.h28v05.005.2017081005823.hdf</InputPointer>
            <InputPointer>MODPTHKM.A2017076.h28v05.005.2017081005813.hdf</InputPointer>
            <InputPointer>MOD09GHK.A2017077.h28v05.005.2017081003543.hdf</InputPointer>
            <InputPointer>MOD09GST.A2017077.h28v05.005.2017081002755.hdf</InputPointer>
            <InputPointer>MODMGGAD.A2017077.h28v05.005.2017081002626.hdf</InputPointer>
            <InputPointer>MODPTHKM.A2017077.h28v05.005.2017081002603.hdf</InputPointer>
            <InputPointer>MOD09GHK.A2017078.h28v05.005.2017080071558.hdf</InputPointer>
            <InputPointer>MOD09GST.A2017078.h28v05.005.2017080070932.hdf</InputPointer>
            <InputPointer>MODMGGAD.A2017078.h28v05.005.2017080070912.hdf</InputPointer>
            <InputPointer>MODPTHKM.A2017078.h28v05.005.2017080070900.hdf</InputPointer>
            <InputPointer>MOD09GHK.A2017079.h28v05.005.2017081060822.hdf</InputPointer>
            <InputPointer>MOD09GST.A2017079.h28v05.005.2017081060423.hdf</InputPointer>
            <InputPointer>MODMGGAD.A2017079.h28v05.005.2017081055503.hdf</InputPointer>
            <InputPointer>MODPTHKM.A2017079.h28v05.005.2017081055458.hdf</InputPointer>
            <InputPointer>MOD09GHK.A2017080.h28v05.005.2017082060748.hdf</InputPointer>
            <InputPointer>MOD09GST.A2017080.h28v05.005.2017082060251.hdf</InputPointer>
            <InputPointer>MODMGGAD.A2017080.h28v05.005.2017082060006.hdf</InputPointer>
            <InputPointer>MODPTHKM.A2017080.h28v05.005.2017082055958.hdf</InputPointer>
            <InputPointer>BRDF_DB.A2001001.h28v05.002.2005235120000.hdf</InputPointer>
        </InputGranule>
        <BrowseProduct>
            <BrowseGranuleId>UR:10:DsShESDTUR:UR:15:DsShSciServerUR:13:[EDC:DSSDSRV]:24:BR:Browse.001:2248137152</BrowseGranuleId>
        </BrowseProduct>
    </GranuleURMetaData>
</GranuleMetaDataFile>
